rplotmaker/__init__.py
rplotmaker-1.0.7.dist-info/LICENSE
rplotmaker-1.0.7.dist-info/METADATA
rplotmaker-1.0.7.dist-info/WHEEL
rplotmaker-1.0.7.dist-info/entry_points.txt
rplotmaker-1.0.7.dist-info/top_level.txt
rplotmaker-1.0.7.dist-info/RECORD
