Metadata-Version: 2.1
Name: rplotmaker
Version: 1.0.7
Summary: R Plot Maker
Home-page: https://gitlab.com/rbuchholz/rplotmaker
Author: Robert Buchholz, Martin Häcker
Author-email: rbu@goodpoint.de, spamfaenger@gmx.de
License: ISC
Classifier: Development Status :: 5 - Production/Stable
Classifier: Environment :: Console
Classifier: Intended Audience :: Developers
Classifier: License :: OSI Approved :: ISC License (ISCL)
Classifier: Programming Language :: Python
Classifier: Programming Language :: Python :: 2.7
Classifier: Programming Language :: Python :: 3
Classifier: Topic :: Scientific/Engineering :: Visualization
License-File: LICENSE
